forgeo/galopy/__init__.py
forgeo/galopy/__version__.py
forgeo/galopy/model.py
forgeo/galopy/neighborhood.py
forgeo/galopy/utils.py
galopy/__init__.py
galopy/__version__.py
galopy/model.py
galopy/neighborhood.py
galopy/utils.py
galopy-0.2.7.post1.dist-info/licenses/LICENSE
galopy-0.2.7.post1.dist-info/METADATA
galopy-0.2.7.post1.dist-info/WHEEL
galopy-0.2.7.post1.dist-info/top_level.txt
galopy-0.2.7.post1.dist-info/RECORD
