Metadata-Version: 2.4
Name: galopy
Version: 0.2.7.post1
Summary: Gstlean Abstraction Library fOr PYthon
Author: Laure Pizzela, Nicolas Clausolles
Author-email: BRGM <forgeo@brgm.fr>
Maintainer-email: Nicolas Clausolles <n.clausolles@brgm.fr>
License:                       GNU GENERAL PUBLIC LICENSE
Project-URL: homepage, https://gitlab.brgm.fr/brgm/geomodelling/spatial/galopy
Project-URL: repository, https://gitlab.brgm.fr/brgm/geomodelling/spatial/galopy
Requires-Python: >=3
License-File: LICENSE
Requires-Dist: numpy
Requires-Dist: gstlearn>=1.8
Provides-Extra: test
Requires-Dist: pytest; extra == "test"
Dynamic: license-file
